{"_path":"/core/getting-started/simple-usage","_dir":"getting-started","_draft":false,"_partial":false,"_locale":"","_empty":false,"title":"Simple usage","description":"Our goal will be making a simple language that convert the text to a LineNode[] array","body":{"type":"root","children":[{"type":"element","tag":"h1","props":{"id":"simple-usage"},"children":[{"type":"text","value":"Simple usage"}]},{"type":"element","tag":"p","props":{},"children":[{"type":"text","value":"Our goal will be making a simple language that convert the text to a "},{"type":"element","tag":"a","props":{"href":"/core/classes/BaseNode"},"children":[{"type":"text","value":"LineNode[]"}]},{"type":"text","value":" array"}]},{"type":"element","tag":"p","props":{},"children":[{"type":"text","value":"That are simple objects that tell us the content of each line of the text."}]},{"type":"element","tag":"p","props":{},"children":[{"type":"text","value":"To do that we will need to define 3 classes for our language Nodes, Processors and a Parser"}]},{"type":"element","tag":"h2","props":{"id":"_1-defining-language-a-nodes"},"children":[{"type":"text","value":"1 - Defining language a nodes"}]},{"type":"element","tag":"p","props":{},"children":[{"type":"text","value":"Is recommended to have an base node with shared methods, and sub nodes with specific methods"}]},{"type":"element","tag":"p","props":{},"children":[{"type":"text","value":"Tokens are simple javascript objects that represents the text."}]},{"type":"element","tag":"p","props":{},"children":[{"type":"text","value":"You can know more about they in "},{"type":"element","tag":"a","props":{"href":"https://www.npmjs.com/package/@language-kit/lexer","rel":["nofollow"]},"children":[{"type":"text","value":"Lexer"}]}]},{"type":"element","tag":"code","props":{"code":"// LineNode.ts\nimport { BaseNode } from '@language-kit/core'\n\nexport class BaseLineNode extends BaseNode {\n    public type = 'BaseLine'\n\n    public sharedMethod() {\n        // code\n    }\n}\n\nexport class FirstLineNode extends BaseLineNode {\n    public type = 'FirstLine'\n\n    public customMethodForFirstLineOnly() {\n        // code\n    }\n}\n","language":"ts","meta":null},"children":[{"type":"element","tag":"pre","props":{},"children":[{"type":"element","tag":"code","props":{"__ignoreMap":""},"children":[{"type":"element","tag":"span","props":{"class":"line","line":1},"children":[{"type":"element","tag":"span","props":{"class":"ct-154281"},"children":[{"type":"text","value":"// LineNode.ts\n"}]}]},{"type":"element","tag":"span","props":{"class":"line","line":2},"children":[{"type":"element","tag":"span","props":{"class":"ct-ee3d45"},"children":[{"type":"text","value":"import"}]},{"type":"element","tag":"span","props":{"class":"ct-b7ae96"},"children":[{"type":"text","value":" { BaseNode } "}]},{"type":"element","tag":"span","props":{"class":"ct-ee3d45"},"children":[{"type":"text","value":"from"}]},{"type":"element","tag":"span","props":{"class":"ct-b7ae96"},"children":[{"type":"text","value":" "}]},{"type":"element","tag":"span","props":{"class":"ct-13faa6"},"children":[{"type":"text","value":"'@language-kit/core'\n"}]}]},{"type":"element","tag":"span","props":{"class":"line","line":3},"children":[{"type":"element","tag":"span","props":{},"children":[{"type":"text","value":"\n"}]}]},{"type":"element","tag":"span","props":{"class":"line","line":4},"children":[{"type":"element","tag":"span","props":{"class":"ct-ee3d45"},"children":[{"type":"text","value":"export"}]},{"type":"element","tag":"span","props":{"class":"ct-b7ae96"},"children":[{"type":"text","value":" "}]},{"type":"element","tag":"span","props":{"class":"ct-ee3d45"},"children":[{"type":"text","value":"class"}]},{"type":"element","tag":"span","props":{"class":"ct-b7ae96"},"children":[{"type":"text","value":" "}]},{"type":"element","tag":"span","props":{"class":"ct-e53488"},"children":[{"type":"text","value":"BaseLineNode"}]},{"type":"element","tag":"span","props":{"class":"ct-b7ae96"},"children":[{"type":"text","value":" "}]},{"type":"element","tag":"span","props":{"class":"ct-ee3d45"},"children":[{"type":"text","value":"extends"}]},{"type":"element","tag":"span","props":{"class":"ct-b7ae96"},"children":[{"type":"text","value":" "}]},{"type":"element","tag":"span","props":{"class":"ct-11bc25"},"children":[{"type":"text","value":"BaseNode"}]},{"type":"element","tag":"span","props":{"class":"ct-b7ae96"},"children":[{"type":"text","value":" {\n"}]}]},{"type":"element","tag":"span","props":{"class":"line","line":5},"children":[{"type":"element","tag":"span","props":{"class":"ct-b7ae96"},"children":[{"type":"text","value":"    "}]},{"type":"element","tag":"span","props":{"class":"ct-ee3d45"},"children":[{"type":"text","value":"public"}]},{"type":"element","tag":"span","props":{"class":"ct-b7ae96"},"children":[{"type":"text","value":" "}]},{"type":"element","tag":"span","props":{"class":"ct-e53488"},"children":[{"type":"text","value":"type"}]},{"type":"element","tag":"span","props":{"class":"ct-b7ae96"},"children":[{"type":"text","value":" "}]},{"type":"element","tag":"span","props":{"class":"ct-ee3d45"},"children":[{"type":"text","value":"="}]},{"type":"element","tag":"span","props":{"class":"ct-b7ae96"},"children":[{"type":"text","value":" "}]},{"type":"element","tag":"span","props":{"class":"ct-13faa6"},"children":[{"type":"text","value":"'BaseLine'\n"}]}]},{"type":"element","tag":"span","props":{"class":"line","line":6},"children":[{"type":"element","tag":"span","props":{},"children":[{"type":"text","value":"\n"}]}]},{"type":"element","tag":"span","props":{"class":"line","line":7},"children":[{"type":"element","tag":"span","props":{"class":"ct-b7ae96"},"children":[{"type":"text","value":"    "}]},{"type":"element","tag":"span","props":{"class":"ct-ee3d45"},"children":[{"type":"text","value":"public"}]},{"type":"element","tag":"span","props":{"class":"ct-b7ae96"},"children":[{"type":"text","value":" "}]},{"type":"element","tag":"span","props":{"class":"ct-b9b64a"},"children":[{"type":"text","value":"sharedMethod"}]},{"type":"element","tag":"span","props":{"class":"ct-b7ae96"},"children":[{"type":"text","value":"() {\n"}]}]},{"type":"element","tag":"span","props":{"class":"line","line":8},"children":[{"type":"element","tag":"span","props":{"class":"ct-b7ae96"},"children":[{"type":"text","value":"        "}]},{"type":"element","tag":"span","props":{"class":"ct-154281"},"children":[{"type":"text","value":"// code\n"}]}]},{"type":"element","tag":"span","props":{"class":"line","line":9},"children":[{"type":"element","tag":"span","props":{"class":"ct-b7ae96"},"children":[{"type":"text","value":"    }\n"}]}]},{"type":"element","tag":"span","props":{"class":"line","line":10},"children":[{"type":"element","tag":"span","props":{"class":"ct-b7ae96"},"children":[{"type":"text","value":"}\n"}]}]},{"type":"element","tag":"span","props":{"class":"line","line":11},"children":[{"type":"element","tag":"span","props":{},"children":[{"type":"text","value":"\n"}]}]},{"type":"element","tag":"span","props":{"class":"line","line":12},"children":[{"type":"element","tag":"span","props":{"class":"ct-ee3d45"},"children":[{"type":"text","value":"export"}]},{"type":"element","tag":"span","props":{"class":"ct-b7ae96"},"children":[{"type":"text","value":" "}]},{"type":"element","tag":"span","props":{"class":"ct-ee3d45"},"children":[{"type":"text","value":"class"}]},{"type":"element","tag":"span","props":{"class":"ct-b7ae96"},"children":[{"type":"text","value":" "}]},{"type":"element","tag":"span","props":{"class":"ct-e53488"},"children":[{"type":"text","value":"FirstLineNode"}]},{"type":"element","tag":"span","props":{"class":"ct-b7ae96"},"children":[{"type":"text","value":" "}]},{"type":"element","tag":"span","props":{"class":"ct-ee3d45"},"children":[{"type":"text","value":"extends"}]},{"type":"element","tag":"span","props":{"class":"ct-b7ae96"},"children":[{"type":"text","value":" "}]},{"type":"element","tag":"span","props":{"class":"ct-11bc25"},"children":[{"type":"text","value":"BaseLineNode"}]},{"type":"element","tag":"span","props":{"class":"ct-b7ae96"},"children":[{"type":"text","value":" {\n"}]}]},{"type":"element","tag":"span","props":{"class":"line","line":13},"children":[{"type":"element","tag":"span","props":{"class":"ct-b7ae96"},"children":[{"type":"text","value":"    "}]},{"type":"element","tag":"span","props":{"class":"ct-ee3d45"},"children":[{"type":"text","value":"public"}]},{"type":"element","tag":"span","props":{"class":"ct-b7ae96"},"children":[{"type":"text","value":" "}]},{"type":"element","tag":"span","props":{"class":"ct-e53488"},"children":[{"type":"text","value":"type"}]},{"type":"element","tag":"span","props":{"class":"ct-b7ae96"},"children":[{"type":"text","value":" "}]},{"type":"element","tag":"span","props":{"class":"ct-ee3d45"},"children":[{"type":"text","value":"="}]},{"type":"element","tag":"span","props":{"class":"ct-b7ae96"},"children":[{"type":"text","value":" "}]},{"type":"element","tag":"span","props":{"class":"ct-13faa6"},"children":[{"type":"text","value":"'FirstLine'\n"}]}]},{"type":"element","tag":"span","props":{"class":"line","line":14},"children":[{"type":"element","tag":"span","props":{},"children":[{"type":"text","value":"\n"}]}]},{"type":"element","tag":"span","props":{"class":"line","line":15},"children":[{"type":"element","tag":"span","props":{"class":"ct-b7ae96"},"children":[{"type":"text","value":"    "}]},{"type":"element","tag":"span","props":{"class":"ct-ee3d45"},"children":[{"type":"text","value":"public"}]},{"type":"element","tag":"span","props":{"class":"ct-b7ae96"},"children":[{"type":"text","value":" "}]},{"type":"element","tag":"span","props":{"class":"ct-b9b64a"},"children":[{"type":"text","value":"customMethodForFirstLineOnly"}]},{"type":"element","tag":"span","props":{"class":"ct-b7ae96"},"children":[{"type":"text","value":"() {\n"}]}]},{"type":"element","tag":"span","props":{"class":"line","line":16},"children":[{"type":"element","tag":"span","props":{"class":"ct-b7ae96"},"children":[{"type":"text","value":"        "}]},{"type":"element","tag":"span","props":{"class":"ct-154281"},"children":[{"type":"text","value":"// code\n"}]}]},{"type":"element","tag":"span","props":{"class":"line","line":17},"children":[{"type":"element","tag":"span","props":{"class":"ct-b7ae96"},"children":[{"type":"text","value":"    }\n"}]}]},{"type":"element","tag":"span","props":{"class":"line","line":18},"children":[{"type":"element","tag":"span","props":{"class":"ct-b7ae96"},"children":[{"type":"text","value":"}"}]}]}]}]}]},{"type":"element","tag":"h2","props":{"id":"_2-define-processor"},"children":[{"type":"text","value":"2 - Define Processor"}]},{"type":"element","tag":"p","props":{},"children":[{"type":"text","value":"Next we have to create an processor to convert tokens to this nodes"}]},{"type":"element","tag":"code","props":{"code":"// LineProcessor.ts\nimport { BaseLineNode, FirstLineNode } from './line-node'\nimport { BaseProcessor } from '@language-kit/core'\n\nexport class LineProcessor extends BaseProcessor<BaseLineNode> {\n    public process() {\n        // current token being processed\n        const token = this.tokens[0]\n\n        // search for the end of line token: token.type = \"BreakLine\"\n        const endOfLineTokenIndex = this.tokens.findIndex((t) => t.type === 'BreakLine')\n\n        // if not found, return false\n        if (endOfLineTokenIndex === -1) return false\n\n        // get all tokens until the end of line token\n        const tokens = this.tokens.slice(this.tokens.indexOf(token), endOfLineTokenIndex + 1)\n\n        let node = new BaseLineNode()\n\n        if (this.nodes.length === 0) {\n            node = new FirstLineNode()\n        }\n\n        node.tokens = tokens\n\n        // add node instance to result nodes\n        this.nodes.push(node)\n\n        // remove tokens processed\n        this.tokens.splice(0, tokens.length)\n\n        // return true to indicate that the processor have processed some tokens and changed the state\n        return true\n    }\n}\n\n","language":"ts","meta":null},"children":[{"type":"element","tag":"pre","props":{},"children":[{"type":"element","tag":"code","props":{"__ignoreMap":""},"children":[{"type":"element","tag":"span","props":{"class":"line","line":1},"children":[{"type":"element","tag":"span","props":{"class":"ct-154281"},"children":[{"type":"text","value":"// LineProcessor.ts\n"}]}]},{"type":"element","tag":"span","props":{"class":"line","line":2},"children":[{"type":"element","tag":"span","props":{"class":"ct-ee3d45"},"children":[{"type":"text","value":"import"}]},{"type":"element","tag":"span","props":{"class":"ct-b7ae96"},"children":[{"type":"text","value":" { BaseLineNode, FirstLineNode } "}]},{"type":"element","tag":"span","props":{"class":"ct-ee3d45"},"children":[{"type":"text","value":"from"}]},{"type":"element","tag":"span","props":{"class":"ct-b7ae96"},"children":[{"type":"text","value":" "}]},{"type":"element","tag":"span","props":{"class":"ct-13faa6"},"children":[{"type":"text","value":"'./line-node'\n"}]}]},{"type":"element","tag":"span","props":{"class":"line","line":3},"children":[{"type":"element","tag":"span","props":{"class":"ct-ee3d45"},"children":[{"type":"text","value":"import"}]},{"type":"element","tag":"span","props":{"class":"ct-b7ae96"},"children":[{"type":"text","value":" { BaseProcessor } "}]},{"type":"element","tag":"span","props":{"class":"ct-ee3d45"},"children":[{"type":"text","value":"from"}]},{"type":"element","tag":"span","props":{"class":"ct-b7ae96"},"children":[{"type":"text","value":" "}]},{"type":"element","tag":"span","props":{"class":"ct-13faa6"},"children":[{"type":"text","value":"'@language-kit/core'\n"}]}]},{"type":"element","tag":"span","props":{"class":"line","line":4},"children":[{"type":"element","tag":"span","props":{},"children":[{"type":"text","value":"\n"}]}]},{"type":"element","tag":"span","props":{"class":"line","line":5},"children":[{"type":"element","tag":"span","props":{"class":"ct-ee3d45"},"children":[{"type":"text","value":"export"}]},{"type":"element","tag":"span","props":{"class":"ct-b7ae96"},"children":[{"type":"text","value":" "}]},{"type":"element","tag":"span","props":{"class":"ct-ee3d45"},"children":[{"type":"text","value":"class"}]},{"type":"element","tag":"span","props":{"class":"ct-b7ae96"},"children":[{"type":"text","value":" "}]},{"type":"element","tag":"span","props":{"class":"ct-e53488"},"children":[{"type":"text","value":"LineProcessor"}]},{"type":"element","tag":"span","props":{"class":"ct-b7ae96"},"children":[{"type":"text","value":" "}]},{"type":"element","tag":"span","props":{"class":"ct-ee3d45"},"children":[{"type":"text","value":"extends"}]},{"type":"element","tag":"span","props":{"class":"ct-b7ae96"},"children":[{"type":"text","value":" "}]},{"type":"element","tag":"span","props":{"class":"ct-11bc25"},"children":[{"type":"text","value":"BaseProcessor"}]},{"type":"element","tag":"span","props":{"class":"ct-b7ae96"},"children":[{"type":"text","value":"<"}]},{"type":"element","tag":"span","props":{"class":"ct-e53488"},"children":[{"type":"text","value":"BaseLineNode"}]},{"type":"element","tag":"span","props":{"class":"ct-b7ae96"},"children":[{"type":"text","value":"> {\n"}]}]},{"type":"element","tag":"span","props":{"class":"line","line":6},"children":[{"type":"element","tag":"span","props":{"class":"ct-b7ae96"},"children":[{"type":"text","value":"    "}]},{"type":"element","tag":"span","props":{"class":"ct-ee3d45"},"children":[{"type":"text","value":"public"}]},{"type":"element","tag":"span","props":{"class":"ct-b7ae96"},"children":[{"type":"text","value":" "}]},{"type":"element","tag":"span","props":{"class":"ct-b9b64a"},"children":[{"type":"text","value":"process"}]},{"type":"element","tag":"span","props":{"class":"ct-b7ae96"},"children":[{"type":"text","value":"() {\n"}]}]},{"type":"element","tag":"span","props":{"class":"line","line":7},"children":[{"type":"element","tag":"span","props":{"class":"ct-b7ae96"},"children":[{"type":"text","value":"        "}]},{"type":"element","tag":"span","props":{"class":"ct-154281"},"children":[{"type":"text","value":"// current token being processed\n"}]}]},{"type":"element","tag":"span","props":{"class":"line","line":8},"children":[{"type":"element","tag":"span","props":{"class":"ct-b7ae96"},"children":[{"type":"text","value":"        "}]},{"type":"element","tag":"span","props":{"class":"ct-ee3d45"},"children":[{"type":"text","value":"const"}]},{"type":"element","tag":"span","props":{"class":"ct-b7ae96"},"children":[{"type":"text","value":" "}]},{"type":"element","tag":"span","props":{"class":"ct-11bc25"},"children":[{"type":"text","value":"token"}]},{"type":"element","tag":"span","props":{"class":"ct-b7ae96"},"children":[{"type":"text","value":" "}]},{"type":"element","tag":"span","props":{"class":"ct-ee3d45"},"children":[{"type":"text","value":"="}]},{"type":"element","tag":"span","props":{"class":"ct-b7ae96"},"children":[{"type":"text","value":" "}]},{"type":"element","tag":"span","props":{"class":"ct-11bc25"},"children":[{"type":"text","value":"this"}]},{"type":"element","tag":"span","props":{"class":"ct-b7ae96"},"children":[{"type":"text","value":".tokens["}]},{"type":"element","tag":"span","props":{"class":"ct-11bc25"},"children":[{"type":"text","value":"0"}]},{"type":"element","tag":"span","props":{"class":"ct-b7ae96"},"children":[{"type":"text","value":"]\n"}]}]},{"type":"element","tag":"span","props":{"class":"line","line":9},"children":[{"type":"element","tag":"span","props":{},"children":[{"type":"text","value":"\n"}]}]},{"type":"element","tag":"span","props":{"class":"line","line":10},"children":[{"type":"element","tag":"span","props":{"class":"ct-b7ae96"},"children":[{"type":"text","value":"        "}]},{"type":"element","tag":"span","props":{"class":"ct-154281"},"children":[{"type":"text","value":"// search for the end of line token: token.type = \"BreakLine\"\n"}]}]},{"type":"element","tag":"span","props":{"class":"line","line":11},"children":[{"type":"element","tag":"span","props":{"class":"ct-b7ae96"},"children":[{"type":"text","value":"        "}]},{"type":"element","tag":"span","props":{"class":"ct-ee3d45"},"children":[{"type":"text","value":"const"}]},{"type":"element","tag":"span","props":{"class":"ct-b7ae96"},"children":[{"type":"text","value":" "}]},{"type":"element","tag":"span","props":{"class":"ct-11bc25"},"children":[{"type":"text","value":"endOfLineTokenIndex"}]},{"type":"element","tag":"span","props":{"class":"ct-b7ae96"},"children":[{"type":"text","value":" "}]},{"type":"element","tag":"span","props":{"class":"ct-ee3d45"},"children":[{"type":"text","value":"="}]},{"type":"element","tag":"span","props":{"class":"ct-b7ae96"},"children":[{"type":"text","value":" "}]},{"type":"element","tag":"span","props":{"class":"ct-11bc25"},"children":[{"type":"text","value":"this"}]},{"type":"element","tag":"span","props":{"class":"ct-b7ae96"},"children":[{"type":"text","value":".tokens."}]},{"type":"element","tag":"span","props":{"class":"ct-b9b64a"},"children":[{"type":"text","value":"findIndex"}]},{"type":"element","tag":"span","props":{"class":"ct-b7ae96"},"children":[{"type":"text","value":"(("}]},{"type":"element","tag":"span","props":{"class":"ct-e53488"},"children":[{"type":"text","value":"t"}]},{"type":"element","tag":"span","props":{"class":"ct-b7ae96"},"children":[{"type":"text","value":") "}]},{"type":"element","tag":"span","props":{"class":"ct-ee3d45"},"children":[{"type":"text","value":"=>"}]},{"type":"element","tag":"span","props":{"class":"ct-b7ae96"},"children":[{"type":"text","value":" t.type "}]},{"type":"element","tag":"span","props":{"class":"ct-ee3d45"},"children":[{"type":"text","value":"==="}]},{"type":"element","tag":"span","props":{"class":"ct-b7ae96"},"children":[{"type":"text","value":" "}]},{"type":"element","tag":"span","props":{"class":"ct-13faa6"},"children":[{"type":"text","value":"'BreakLine'"}]},{"type":"element","tag":"span","props":{"class":"ct-b7ae96"},"children":[{"type":"text","value":")\n"}]}]},{"type":"element","tag":"span","props":{"class":"line","line":12},"children":[{"type":"element","tag":"span","props":{},"children":[{"type":"text","value":"\n"}]}]},{"type":"element","tag":"span","props":{"class":"line","line":13},"children":[{"type":"element","tag":"span","props":{"class":"ct-b7ae96"},"children":[{"type":"text","value":"        "}]},{"type":"element","tag":"span","props":{"class":"ct-154281"},"children":[{"type":"text","value":"// if not found, return false\n"}]}]},{"type":"element","tag":"span","props":{"class":"line","line":14},"children":[{"type":"element","tag":"span","props":{"class":"ct-b7ae96"},"children":[{"type":"text","value":"        "}]},{"type":"element","tag":"span","props":{"class":"ct-ee3d45"},"children":[{"type":"text","value":"if"}]},{"type":"element","tag":"span","props":{"class":"ct-b7ae96"},"children":[{"type":"text","value":" (endOfLineTokenIndex "}]},{"type":"element","tag":"span","props":{"class":"ct-ee3d45"},"children":[{"type":"text","value":"==="}]},{"type":"element","tag":"span","props":{"class":"ct-b7ae96"},"children":[{"type":"text","value":" "}]},{"type":"element","tag":"span","props":{"class":"ct-ee3d45"},"children":[{"type":"text","value":"-"}]},{"type":"element","tag":"span","props":{"class":"ct-11bc25"},"children":[{"type":"text","value":"1"}]},{"type":"element","tag":"span","props":{"class":"ct-b7ae96"},"children":[{"type":"text","value":") "}]},{"type":"element","tag":"span","props":{"class":"ct-ee3d45"},"children":[{"type":"text","value":"return"}]},{"type":"element","tag":"span","props":{"class":"ct-b7ae96"},"children":[{"type":"text","value":" "}]},{"type":"element","tag":"span","props":{"class":"ct-11bc25"},"children":[{"type":"text","value":"false\n"}]}]},{"type":"element","tag":"span","props":{"class":"line","line":15},"children":[{"type":"element","tag":"span","props":{},"children":[{"type":"text","value":"\n"}]}]},{"type":"element","tag":"span","props":{"class":"line","line":16},"children":[{"type":"element","tag":"span","props":{"class":"ct-b7ae96"},"children":[{"type":"text","value":"        "}]},{"type":"element","tag":"span","props":{"class":"ct-154281"},"children":[{"type":"text","value":"// get all tokens until the end of line token\n"}]}]},{"type":"element","tag":"span","props":{"class":"line","line":17},"children":[{"type":"element","tag":"span","props":{"class":"ct-b7ae96"},"children":[{"type":"text","value":"        "}]},{"type":"element","tag":"span","props":{"class":"ct-ee3d45"},"children":[{"type":"text","value":"const"}]},{"type":"element","tag":"span","props":{"class":"ct-b7ae96"},"children":[{"type":"text","value":" "}]},{"type":"element","tag":"span","props":{"class":"ct-11bc25"},"children":[{"type":"text","value":"tokens"}]},{"type":"element","tag":"span","props":{"class":"ct-b7ae96"},"children":[{"type":"text","value":" "}]},{"type":"element","tag":"span","props":{"class":"ct-ee3d45"},"children":[{"type":"text","value":"="}]},{"type":"element","tag":"span","props":{"class":"ct-b7ae96"},"children":[{"type":"text","value":" "}]},{"type":"element","tag":"span","props":{"class":"ct-11bc25"},"children":[{"type":"text","value":"this"}]},{"type":"element","tag":"span","props":{"class":"ct-b7ae96"},"children":[{"type":"text","value":".tokens."}]},{"type":"element","tag":"span","props":{"class":"ct-b9b64a"},"children":[{"type":"text","value":"slice"}]},{"type":"element","tag":"span","props":{"class":"ct-b7ae96"},"children":[{"type":"text","value":"("}]},{"type":"element","tag":"span","props":{"class":"ct-11bc25"},"children":[{"type":"text","value":"this"}]},{"type":"element","tag":"span","props":{"class":"ct-b7ae96"},"children":[{"type":"text","value":".tokens."}]},{"type":"element","tag":"span","props":{"class":"ct-b9b64a"},"children":[{"type":"text","value":"indexOf"}]},{"type":"element","tag":"span","props":{"class":"ct-b7ae96"},"children":[{"type":"text","value":"(token), endOfLineTokenIndex "}]},{"type":"element","tag":"span","props":{"class":"ct-ee3d45"},"children":[{"type":"text","value":"+"}]},{"type":"element","tag":"span","props":{"class":"ct-b7ae96"},"children":[{"type":"text","value":" "}]},{"type":"element","tag":"span","props":{"class":"ct-11bc25"},"children":[{"type":"text","value":"1"}]},{"type":"element","tag":"span","props":{"class":"ct-b7ae96"},"children":[{"type":"text","value":")\n"}]}]},{"type":"element","tag":"span","props":{"class":"line","line":18},"children":[{"type":"element","tag":"span","props":{},"children":[{"type":"text","value":"\n"}]}]},{"type":"element","tag":"span","props":{"class":"line","line":19},"children":[{"type":"element","tag":"span","props":{"class":"ct-b7ae96"},"children":[{"type":"text","value":"        "}]},{"type":"element","tag":"span","props":{"class":"ct-ee3d45"},"children":[{"type":"text","value":"let"}]},{"type":"element","tag":"span","props":{"class":"ct-b7ae96"},"children":[{"type":"text","value":" node "}]},{"type":"element","tag":"span","props":{"class":"ct-ee3d45"},"children":[{"type":"text","value":"="}]},{"type":"element","tag":"span","props":{"class":"ct-b7ae96"},"children":[{"type":"text","value":" "}]},{"type":"element","tag":"span","props":{"class":"ct-ee3d45"},"children":[{"type":"text","value":"new"}]},{"type":"element","tag":"span","props":{"class":"ct-b7ae96"},"children":[{"type":"text","value":" "}]},{"type":"element","tag":"span","props":{"class":"ct-b9b64a"},"children":[{"type":"text","value":"BaseLineNode"}]},{"type":"element","tag":"span","props":{"class":"ct-b7ae96"},"children":[{"type":"text","value":"()\n"}]}]},{"type":"element","tag":"span","props":{"class":"line","line":20},"children":[{"type":"element","tag":"span","props":{},"children":[{"type":"text","value":"\n"}]}]},{"type":"element","tag":"span","props":{"class":"line","line":21},"children":[{"type":"element","tag":"span","props":{"class":"ct-b7ae96"},"children":[{"type":"text","value":"        "}]},{"type":"element","tag":"span","props":{"class":"ct-ee3d45"},"children":[{"type":"text","value":"if"}]},{"type":"element","tag":"span","props":{"class":"ct-b7ae96"},"children":[{"type":"text","value":" ("}]},{"type":"element","tag":"span","props":{"class":"ct-11bc25"},"children":[{"type":"text","value":"this"}]},{"type":"element","tag":"span","props":{"class":"ct-b7ae96"},"children":[{"type":"text","value":".nodes."}]},{"type":"element","tag":"span","props":{"class":"ct-11bc25"},"children":[{"type":"text","value":"length"}]},{"type":"element","tag":"span","props":{"class":"ct-b7ae96"},"children":[{"type":"text","value":" "}]},{"type":"element","tag":"span","props":{"class":"ct-ee3d45"},"children":[{"type":"text","value":"==="}]},{"type":"element","tag":"span","props":{"class":"ct-b7ae96"},"children":[{"type":"text","value":" "}]},{"type":"element","tag":"span","props":{"class":"ct-11bc25"},"children":[{"type":"text","value":"0"}]},{"type":"element","tag":"span","props":{"class":"ct-b7ae96"},"children":[{"type":"text","value":") {\n"}]}]},{"type":"element","tag":"span","props":{"class":"line","line":22},"children":[{"type":"element","tag":"span","props":{"class":"ct-b7ae96"},"children":[{"type":"text","value":"            node "}]},{"type":"element","tag":"span","props":{"class":"ct-ee3d45"},"children":[{"type":"text","value":"="}]},{"type":"element","tag":"span","props":{"class":"ct-b7ae96"},"children":[{"type":"text","value":" "}]},{"type":"element","tag":"span","props":{"class":"ct-ee3d45"},"children":[{"type":"text","value":"new"}]},{"type":"element","tag":"span","props":{"class":"ct-b7ae96"},"children":[{"type":"text","value":" "}]},{"type":"element","tag":"span","props":{"class":"ct-b9b64a"},"children":[{"type":"text","value":"FirstLineNode"}]},{"type":"element","tag":"span","props":{"class":"ct-b7ae96"},"children":[{"type":"text","value":"()\n"}]}]},{"type":"element","tag":"span","props":{"class":"line","line":23},"children":[{"type":"element","tag":"span","props":{"class":"ct-b7ae96"},"children":[{"type":"text","value":"        }\n"}]}]},{"type":"element","tag":"span","props":{"class":"line","line":24},"children":[{"type":"element","tag":"span","props":{},"children":[{"type":"text","value":"\n"}]}]},{"type":"element","tag":"span","props":{"class":"line","line":25},"children":[{"type":"element","tag":"span","props":{"class":"ct-b7ae96"},"children":[{"type":"text","value":"        node.tokens "}]},{"type":"element","tag":"span","props":{"class":"ct-ee3d45"},"children":[{"type":"text","value":"="}]},{"type":"element","tag":"span","props":{"class":"ct-b7ae96"},"children":[{"type":"text","value":" tokens\n"}]}]},{"type":"element","tag":"span","props":{"class":"line","line":26},"children":[{"type":"element","tag":"span","props":{},"children":[{"type":"text","value":"\n"}]}]},{"type":"element","tag":"span","props":{"class":"line","line":27},"children":[{"type":"element","tag":"span","props":{"class":"ct-b7ae96"},"children":[{"type":"text","value":"        "}]},{"type":"element","tag":"span","props":{"class":"ct-154281"},"children":[{"type":"text","value":"// add node instance to result nodes\n"}]}]},{"type":"element","tag":"span","props":{"class":"line","line":28},"children":[{"type":"element","tag":"span","props":{"class":"ct-b7ae96"},"children":[{"type":"text","value":"        "}]},{"type":"element","tag":"span","props":{"class":"ct-11bc25"},"children":[{"type":"text","value":"this"}]},{"type":"element","tag":"span","props":{"class":"ct-b7ae96"},"children":[{"type":"text","value":".nodes."}]},{"type":"element","tag":"span","props":{"class":"ct-b9b64a"},"children":[{"type":"text","value":"push"}]},{"type":"element","tag":"span","props":{"class":"ct-b7ae96"},"children":[{"type":"text","value":"(node)\n"}]}]},{"type":"element","tag":"span","props":{"class":"line","line":29},"children":[{"type":"element","tag":"span","props":{},"children":[{"type":"text","value":"\n"}]}]},{"type":"element","tag":"span","props":{"class":"line","line":30},"children":[{"type":"element","tag":"span","props":{"class":"ct-b7ae96"},"children":[{"type":"text","value":"        "}]},{"type":"element","tag":"span","props":{"class":"ct-154281"},"children":[{"type":"text","value":"// remove tokens processed\n"}]}]},{"type":"element","tag":"span","props":{"class":"line","line":31},"children":[{"type":"element","tag":"span","props":{"class":"ct-b7ae96"},"children":[{"type":"text","value":"        "}]},{"type":"element","tag":"span","props":{"class":"ct-11bc25"},"children":[{"type":"text","value":"this"}]},{"type":"element","tag":"span","props":{"class":"ct-b7ae96"},"children":[{"type":"text","value":".tokens."}]},{"type":"element","tag":"span","props":{"class":"ct-b9b64a"},"children":[{"type":"text","value":"splice"}]},{"type":"element","tag":"span","props":{"class":"ct-b7ae96"},"children":[{"type":"text","value":"("}]},{"type":"element","tag":"span","props":{"class":"ct-11bc25"},"children":[{"type":"text","value":"0"}]},{"type":"element","tag":"span","props":{"class":"ct-b7ae96"},"children":[{"type":"text","value":", tokens."}]},{"type":"element","tag":"span","props":{"class":"ct-11bc25"},"children":[{"type":"text","value":"length"}]},{"type":"element","tag":"span","props":{"class":"ct-b7ae96"},"children":[{"type":"text","value":")\n"}]}]},{"type":"element","tag":"span","props":{"class":"line","line":32},"children":[{"type":"element","tag":"span","props":{},"children":[{"type":"text","value":"\n"}]}]},{"type":"element","tag":"span","props":{"class":"line","line":33},"children":[{"type":"element","tag":"span","props":{"class":"ct-b7ae96"},"children":[{"type":"text","value":"        "}]},{"type":"element","tag":"span","props":{"class":"ct-154281"},"children":[{"type":"text","value":"// return true to indicate that the processor have processed some tokens and changed the state\n"}]}]},{"type":"element","tag":"span","props":{"class":"line","line":34},"children":[{"type":"element","tag":"span","props":{"class":"ct-b7ae96"},"children":[{"type":"text","value":"        "}]},{"type":"element","tag":"span","props":{"class":"ct-ee3d45"},"children":[{"type":"text","value":"return"}]},{"type":"element","tag":"span","props":{"class":"ct-b7ae96"},"children":[{"type":"text","value":" "}]},{"type":"element","tag":"span","props":{"class":"ct-11bc25"},"children":[{"type":"text","value":"true\n"}]}]},{"type":"element","tag":"span","props":{"class":"line","line":35},"children":[{"type":"element","tag":"span","props":{"class":"ct-b7ae96"},"children":[{"type":"text","value":"    }\n"}]}]},{"type":"element","tag":"span","props":{"class":"line","line":36},"children":[{"type":"element","tag":"span","props":{"class":"ct-b7ae96"},"children":[{"type":"text","value":"}"}]}]}]}]}]},{"type":"element","tag":"h2","props":{"id":"_3-define-parser"},"children":[{"type":"text","value":"3 - Define parser"}]},{"type":"element","tag":"p","props":{},"children":[{"type":"text","value":"Finally we can create an parser with the created classes."}]},{"type":"element","tag":"code","props":{"code":"import { BaseParser } from '@language-kit/core'\nimport { BaseLineNode } from './LineNode'\nimport { LineProcessor } from './LineProcessor'\n\nexport class LineParser extends BaseParser<BaseLineNode> {\n     constructor() {\n        super()\n\n        this.setProcessors([\n            LineProcessor\n        ])\n    }\n\n    public onUnhandledToken: BaseParser['onUnhandledToken'] = (token) => {\n        console.error('unhandled token', token)\n    }\n}\n\n","language":"ts","meta":null},"children":[{"type":"element","tag":"pre","props":{},"children":[{"type":"element","tag":"code","props":{"__ignoreMap":""},"children":[{"type":"element","tag":"span","props":{"class":"line","line":1},"children":[{"type":"element","tag":"span","props":{"class":"ct-ee3d45"},"children":[{"type":"text","value":"import"}]},{"type":"element","tag":"span","props":{"class":"ct-b7ae96"},"children":[{"type":"text","value":" { BaseParser } "}]},{"type":"element","tag":"span","props":{"class":"ct-ee3d45"},"children":[{"type":"text","value":"from"}]},{"type":"element","tag":"span","props":{"class":"ct-b7ae96"},"children":[{"type":"text","value":" "}]},{"type":"element","tag":"span","props":{"class":"ct-13faa6"},"children":[{"type":"text","value":"'@language-kit/core'\n"}]}]},{"type":"element","tag":"span","props":{"class":"line","line":2},"children":[{"type":"element","tag":"span","props":{"class":"ct-ee3d45"},"children":[{"type":"text","value":"import"}]},{"type":"element","tag":"span","props":{"class":"ct-b7ae96"},"children":[{"type":"text","value":" { BaseLineNode } "}]},{"type":"element","tag":"span","props":{"class":"ct-ee3d45"},"children":[{"type":"text","value":"from"}]},{"type":"element","tag":"span","props":{"class":"ct-b7ae96"},"children":[{"type":"text","value":" "}]},{"type":"element","tag":"span","props":{"class":"ct-13faa6"},"children":[{"type":"text","value":"'./LineNode'\n"}]}]},{"type":"element","tag":"span","props":{"class":"line","line":3},"children":[{"type":"element","tag":"span","props":{"class":"ct-ee3d45"},"children":[{"type":"text","value":"import"}]},{"type":"element","tag":"span","props":{"class":"ct-b7ae96"},"children":[{"type":"text","value":" { LineProcessor } "}]},{"type":"element","tag":"span","props":{"class":"ct-ee3d45"},"children":[{"type":"text","value":"from"}]},{"type":"element","tag":"span","props":{"class":"ct-b7ae96"},"children":[{"type":"text","value":" "}]},{"type":"element","tag":"span","props":{"class":"ct-13faa6"},"children":[{"type":"text","value":"'./LineProcessor'\n"}]}]},{"type":"element","tag":"span","props":{"class":"line","line":4},"children":[{"type":"element","tag":"span","props":{},"children":[{"type":"text","value":"\n"}]}]},{"type":"element","tag":"span","props":{"class":"line","line":5},"children":[{"type":"element","tag":"span","props":{"class":"ct-ee3d45"},"children":[{"type":"text","value":"export"}]},{"type":"element","tag":"span","props":{"class":"ct-b7ae96"},"children":[{"type":"text","value":" "}]},{"type":"element","tag":"span","props":{"class":"ct-ee3d45"},"children":[{"type":"text","value":"class"}]},{"type":"element","tag":"span","props":{"class":"ct-b7ae96"},"children":[{"type":"text","value":" "}]},{"type":"element","tag":"span","props":{"class":"ct-e53488"},"children":[{"type":"text","value":"LineParser"}]},{"type":"element","tag":"span","props":{"class":"ct-b7ae96"},"children":[{"type":"text","value":" "}]},{"type":"element","tag":"span","props":{"class":"ct-ee3d45"},"children":[{"type":"text","value":"extends"}]},{"type":"element","tag":"span","props":{"class":"ct-b7ae96"},"children":[{"type":"text","value":" "}]},{"type":"element","tag":"span","props":{"class":"ct-11bc25"},"children":[{"type":"text","value":"BaseParser"}]},{"type":"element","tag":"span","props":{"class":"ct-b7ae96"},"children":[{"type":"text","value":"<"}]},{"type":"element","tag":"span","props":{"class":"ct-e53488"},"children":[{"type":"text","value":"BaseLineNode"}]},{"type":"element","tag":"span","props":{"class":"ct-b7ae96"},"children":[{"type":"text","value":"> {\n"}]}]},{"type":"element","tag":"span","props":{"class":"line","line":6},"children":[{"type":"element","tag":"span","props":{"class":"ct-b7ae96"},"children":[{"type":"text","value":"     "}]},{"type":"element","tag":"span","props":{"class":"ct-ee3d45"},"children":[{"type":"text","value":"constructor"}]},{"type":"element","tag":"span","props":{"class":"ct-b7ae96"},"children":[{"type":"text","value":"() {\n"}]}]},{"type":"element","tag":"span","props":{"class":"line","line":7},"children":[{"type":"element","tag":"span","props":{"class":"ct-b7ae96"},"children":[{"type":"text","value":"        "}]},{"type":"element","tag":"span","props":{"class":"ct-11bc25"},"children":[{"type":"text","value":"super"}]},{"type":"element","tag":"span","props":{"class":"ct-b7ae96"},"children":[{"type":"text","value":"()\n"}]}]},{"type":"element","tag":"span","props":{"class":"line","line":8},"children":[{"type":"element","tag":"span","props":{},"children":[{"type":"text","value":"\n"}]}]},{"type":"element","tag":"span","props":{"class":"line","line":9},"children":[{"type":"element","tag":"span","props":{"class":"ct-b7ae96"},"children":[{"type":"text","value":"        "}]},{"type":"element","tag":"span","props":{"class":"ct-11bc25"},"children":[{"type":"text","value":"this"}]},{"type":"element","tag":"span","props":{"class":"ct-b7ae96"},"children":[{"type":"text","value":"."}]},{"type":"element","tag":"span","props":{"class":"ct-b9b64a"},"children":[{"type":"text","value":"setProcessors"}]},{"type":"element","tag":"span","props":{"class":"ct-b7ae96"},"children":[{"type":"text","value":"([\n"}]}]},{"type":"element","tag":"span","props":{"class":"line","line":10},"children":[{"type":"element","tag":"span","props":{"class":"ct-b7ae96"},"children":[{"type":"text","value":"            LineProcessor\n"}]}]},{"type":"element","tag":"span","props":{"class":"line","line":11},"children":[{"type":"element","tag":"span","props":{"class":"ct-b7ae96"},"children":[{"type":"text","value":"        ])\n"}]}]},{"type":"element","tag":"span","props":{"class":"line","line":12},"children":[{"type":"element","tag":"span","props":{"class":"ct-b7ae96"},"children":[{"type":"text","value":"    }\n"}]}]},{"type":"element","tag":"span","props":{"class":"line","line":13},"children":[{"type":"element","tag":"span","props":{},"children":[{"type":"text","value":"\n"}]}]},{"type":"element","tag":"span","props":{"class":"line","line":14},"children":[{"type":"element","tag":"span","props":{"class":"ct-b7ae96"},"children":[{"type":"text","value":"    "}]},{"type":"element","tag":"span","props":{"class":"ct-ee3d45"},"children":[{"type":"text","value":"public"}]},{"type":"element","tag":"span","props":{"class":"ct-b7ae96"},"children":[{"type":"text","value":" "}]},{"type":"element","tag":"span","props":{"class":"ct-b9b64a"},"children":[{"type":"text","value":"onUnhandledToken"}]},{"type":"element","tag":"span","props":{"class":"ct-ee3d45"},"children":[{"type":"text","value":":"}]},{"type":"element","tag":"span","props":{"class":"ct-b7ae96"},"children":[{"type":"text","value":" "}]},{"type":"element","tag":"span","props":{"class":"ct-e53488"},"children":[{"type":"text","value":"BaseParser"}]},{"type":"element","tag":"span","props":{"class":"ct-b7ae96"},"children":[{"type":"text","value":"["}]},{"type":"element","tag":"span","props":{"class":"ct-13faa6"},"children":[{"type":"text","value":"'onUnhandledToken'"}]},{"type":"element","tag":"span","props":{"class":"ct-b7ae96"},"children":[{"type":"text","value":"] "}]},{"type":"element","tag":"span","props":{"class":"ct-ee3d45"},"children":[{"type":"text","value":"="}]},{"type":"element","tag":"span","props":{"class":"ct-b7ae96"},"children":[{"type":"text","value":" ("}]},{"type":"element","tag":"span","props":{"class":"ct-e53488"},"children":[{"type":"text","value":"token"}]},{"type":"element","tag":"span","props":{"class":"ct-b7ae96"},"children":[{"type":"text","value":") "}]},{"type":"element","tag":"span","props":{"class":"ct-ee3d45"},"children":[{"type":"text","value":"=>"}]},{"type":"element","tag":"span","props":{"class":"ct-b7ae96"},"children":[{"type":"text","value":" {\n"}]}]},{"type":"element","tag":"span","props":{"class":"line","line":15},"children":[{"type":"element","tag":"span","props":{"class":"ct-b7ae96"},"children":[{"type":"text","value":"        console."}]},{"type":"element","tag":"span","props":{"class":"ct-b9b64a"},"children":[{"type":"text","value":"error"}]},{"type":"element","tag":"span","props":{"class":"ct-b7ae96"},"children":[{"type":"text","value":"("}]},{"type":"element","tag":"span","props":{"class":"ct-13faa6"},"children":[{"type":"text","value":"'unhandled token'"}]},{"type":"element","tag":"span","props":{"class":"ct-b7ae96"},"children":[{"type":"text","value":", token)\n"}]}]},{"type":"element","tag":"span","props":{"class":"line","line":16},"children":[{"type":"element","tag":"span","props":{"class":"ct-b7ae96"},"children":[{"type":"text","value":"    }\n"}]}]},{"type":"element","tag":"span","props":{"class":"line","line":17},"children":[{"type":"element","tag":"span","props":{"class":"ct-b7ae96"},"children":[{"type":"text","value":"}"}]}]}]}]}]},{"type":"element","tag":"h2","props":{"id":"_4-use-the-parse"},"children":[{"type":"text","value":"4 - Use the Parse"}]},{"type":"element","tag":"p","props":{},"children":[{"type":"text","value":"Now we can parse any string and have an the output desired"}]},{"type":"element","tag":"code","props":{"code":"// Sample.ts\nimport { LineParser } from './LineParser'\nimport { FirstLineNode } from './line-node'\n\nconst parser = new LineParser()\n\nconst payload = ['Hello', '', 'This is a paragraph'].join('\\n')\n\nconst [firstLine, normalLine] = parser.toNodes(payload) // result [FirstLineNode, BaseLineNode]\n\nnormalLine.sharedMethod()\n\nif (firstLine instanceof FirstLineNode) {\n    firstLine.customMethodForFirstLineOnly()\n}\n\n","language":"ts","meta":null},"children":[{"type":"element","tag":"pre","props":{},"children":[{"type":"element","tag":"code","props":{"__ignoreMap":""},"children":[{"type":"element","tag":"span","props":{"class":"line","line":1},"children":[{"type":"element","tag":"span","props":{"class":"ct-154281"},"children":[{"type":"text","value":"// Sample.ts\n"}]}]},{"type":"element","tag":"span","props":{"class":"line","line":2},"children":[{"type":"element","tag":"span","props":{"class":"ct-ee3d45"},"children":[{"type":"text","value":"import"}]},{"type":"element","tag":"span","props":{"class":"ct-b7ae96"},"children":[{"type":"text","value":" { LineParser } "}]},{"type":"element","tag":"span","props":{"class":"ct-ee3d45"},"children":[{"type":"text","value":"from"}]},{"type":"element","tag":"span","props":{"class":"ct-b7ae96"},"children":[{"type":"text","value":" "}]},{"type":"element","tag":"span","props":{"class":"ct-13faa6"},"children":[{"type":"text","value":"'./LineParser'\n"}]}]},{"type":"element","tag":"span","props":{"class":"line","line":3},"children":[{"type":"element","tag":"span","props":{"class":"ct-ee3d45"},"children":[{"type":"text","value":"import"}]},{"type":"element","tag":"span","props":{"class":"ct-b7ae96"},"children":[{"type":"text","value":" { FirstLineNode } "}]},{"type":"element","tag":"span","props":{"class":"ct-ee3d45"},"children":[{"type":"text","value":"from"}]},{"type":"element","tag":"span","props":{"class":"ct-b7ae96"},"children":[{"type":"text","value":" "}]},{"type":"element","tag":"span","props":{"class":"ct-13faa6"},"children":[{"type":"text","value":"'./line-node'\n"}]}]},{"type":"element","tag":"span","props":{"class":"line","line":4},"children":[{"type":"element","tag":"span","props":{},"children":[{"type":"text","value":"\n"}]}]},{"type":"element","tag":"span","props":{"class":"line","line":5},"children":[{"type":"element","tag":"span","props":{"class":"ct-ee3d45"},"children":[{"type":"text","value":"const"}]},{"type":"element","tag":"span","props":{"class":"ct-b7ae96"},"children":[{"type":"text","value":" "}]},{"type":"element","tag":"span","props":{"class":"ct-11bc25"},"children":[{"type":"text","value":"parser"}]},{"type":"element","tag":"span","props":{"class":"ct-b7ae96"},"children":[{"type":"text","value":" "}]},{"type":"element","tag":"span","props":{"class":"ct-ee3d45"},"children":[{"type":"text","value":"="}]},{"type":"element","tag":"span","props":{"class":"ct-b7ae96"},"children":[{"type":"text","value":" "}]},{"type":"element","tag":"span","props":{"class":"ct-ee3d45"},"children":[{"type":"text","value":"new"}]},{"type":"element","tag":"span","props":{"class":"ct-b7ae96"},"children":[{"type":"text","value":" "}]},{"type":"element","tag":"span","props":{"class":"ct-b9b64a"},"children":[{"type":"text","value":"LineParser"}]},{"type":"element","tag":"span","props":{"class":"ct-b7ae96"},"children":[{"type":"text","value":"()\n"}]}]},{"type":"element","tag":"span","props":{"class":"line","line":6},"children":[{"type":"element","tag":"span","props":{},"children":[{"type":"text","value":"\n"}]}]},{"type":"element","tag":"span","props":{"class":"line","line":7},"children":[{"type":"element","tag":"span","props":{"class":"ct-ee3d45"},"children":[{"type":"text","value":"const"}]},{"type":"element","tag":"span","props":{"class":"ct-b7ae96"},"children":[{"type":"text","value":" "}]},{"type":"element","tag":"span","props":{"class":"ct-11bc25"},"children":[{"type":"text","value":"payload"}]},{"type":"element","tag":"span","props":{"class":"ct-b7ae96"},"children":[{"type":"text","value":" "}]},{"type":"element","tag":"span","props":{"class":"ct-ee3d45"},"children":[{"type":"text","value":"="}]},{"type":"element","tag":"span","props":{"class":"ct-b7ae96"},"children":[{"type":"text","value":" ["}]},{"type":"element","tag":"span","props":{"class":"ct-13faa6"},"children":[{"type":"text","value":"'Hello'"}]},{"type":"element","tag":"span","props":{"class":"ct-b7ae96"},"children":[{"type":"text","value":", "}]},{"type":"element","tag":"span","props":{"class":"ct-13faa6"},"children":[{"type":"text","value":"''"}]},{"type":"element","tag":"span","props":{"class":"ct-b7ae96"},"children":[{"type":"text","value":", "}]},{"type":"element","tag":"span","props":{"class":"ct-13faa6"},"children":[{"type":"text","value":"'This is a paragraph'"}]},{"type":"element","tag":"span","props":{"class":"ct-b7ae96"},"children":[{"type":"text","value":"]."}]},{"type":"element","tag":"span","props":{"class":"ct-b9b64a"},"children":[{"type":"text","value":"join"}]},{"type":"element","tag":"span","props":{"class":"ct-b7ae96"},"children":[{"type":"text","value":"("}]},{"type":"element","tag":"span","props":{"class":"ct-13faa6"},"children":[{"type":"text","value":"'"}]},{"type":"element","tag":"span","props":{"class":"ct-11bc25"},"children":[{"type":"text","value":"\\n"}]},{"type":"element","tag":"span","props":{"class":"ct-13faa6"},"children":[{"type":"text","value":"'"}]},{"type":"element","tag":"span","props":{"class":"ct-b7ae96"},"children":[{"type":"text","value":")\n"}]}]},{"type":"element","tag":"span","props":{"class":"line","line":8},"children":[{"type":"element","tag":"span","props":{},"children":[{"type":"text","value":"\n"}]}]},{"type":"element","tag":"span","props":{"class":"line","line":9},"children":[{"type":"element","tag":"span","props":{"class":"ct-ee3d45"},"children":[{"type":"text","value":"const"}]},{"type":"element","tag":"span","props":{"class":"ct-b7ae96"},"children":[{"type":"text","value":" ["}]},{"type":"element","tag":"span","props":{"class":"ct-11bc25"},"children":[{"type":"text","value":"firstLine"}]},{"type":"element","tag":"span","props":{"class":"ct-b7ae96"},"children":[{"type":"text","value":", "}]},{"type":"element","tag":"span","props":{"class":"ct-11bc25"},"children":[{"type":"text","value":"normalLine"}]},{"type":"element","tag":"span","props":{"class":"ct-b7ae96"},"children":[{"type":"text","value":"] "}]},{"type":"element","tag":"span","props":{"class":"ct-ee3d45"},"children":[{"type":"text","value":"="}]},{"type":"element","tag":"span","props":{"class":"ct-b7ae96"},"children":[{"type":"text","value":" parser."}]},{"type":"element","tag":"span","props":{"class":"ct-b9b64a"},"children":[{"type":"text","value":"toNodes"}]},{"type":"element","tag":"span","props":{"class":"ct-b7ae96"},"children":[{"type":"text","value":"(payload) "}]},{"type":"element","tag":"span","props":{"class":"ct-154281"},"children":[{"type":"text","value":"// result [FirstLineNode, BaseLineNode]\n"}]}]},{"type":"element","tag":"span","props":{"class":"line","line":10},"children":[{"type":"element","tag":"span","props":{},"children":[{"type":"text","value":"\n"}]}]},{"type":"element","tag":"span","props":{"class":"line","line":11},"children":[{"type":"element","tag":"span","props":{"class":"ct-b7ae96"},"children":[{"type":"text","value":"normalLine."}]},{"type":"element","tag":"span","props":{"class":"ct-b9b64a"},"children":[{"type":"text","value":"sharedMethod"}]},{"type":"element","tag":"span","props":{"class":"ct-b7ae96"},"children":[{"type":"text","value":"()\n"}]}]},{"type":"element","tag":"span","props":{"class":"line","line":12},"children":[{"type":"element","tag":"span","props":{},"children":[{"type":"text","value":"\n"}]}]},{"type":"element","tag":"span","props":{"class":"line","line":13},"children":[{"type":"element","tag":"span","props":{"class":"ct-ee3d45"},"children":[{"type":"text","value":"if"}]},{"type":"element","tag":"span","props":{"class":"ct-b7ae96"},"children":[{"type":"text","value":" (firstLine "}]},{"type":"element","tag":"span","props":{"class":"ct-ee3d45"},"children":[{"type":"text","value":"instanceof"}]},{"type":"element","tag":"span","props":{"class":"ct-b7ae96"},"children":[{"type":"text","value":" "}]},{"type":"element","tag":"span","props":{"class":"ct-e53488"},"children":[{"type":"text","value":"FirstLineNode"}]},{"type":"element","tag":"span","props":{"class":"ct-b7ae96"},"children":[{"type":"text","value":") {\n"}]}]},{"type":"element","tag":"span","props":{"class":"line","line":14},"children":[{"type":"element","tag":"span","props":{"class":"ct-b7ae96"},"children":[{"type":"text","value":"    firstLine."}]},{"type":"element","tag":"span","props":{"class":"ct-b9b64a"},"children":[{"type":"text","value":"customMethodForFirstLineOnly"}]},{"type":"element","tag":"span","props":{"class":"ct-b7ae96"},"children":[{"type":"text","value":"()\n"}]}]},{"type":"element","tag":"span","props":{"class":"line","line":15},"children":[{"type":"element","tag":"span","props":{"class":"ct-b7ae96"},"children":[{"type":"text","value":"}"}]}]}]}]}]},{"type":"element","tag":"style","children":[{"type":"text","value":".ct-b9b64a{color:#8250DF}\n.ct-11bc25{color:#0550AE}\n.ct-e53488{color:#953800}\n.ct-13faa6{color:#0A3069}\n.ct-b7ae96{color:#24292F}\n.ct-ee3d45{color:#CF222E}\n.ct-154281{color:#6E7781}\n.dark .ct-154281{color:#8B949E}\n.dark .ct-ee3d45{color:#FF7B72}\n.dark .ct-b7ae96{color:#C9D1D9}\n.dark .ct-13faa6{color:#A5D6FF}\n.dark .ct-e53488{color:#FFA657}\n.dark .ct-11bc25{color:#79C0FF}\n.dark .ct-b9b64a{color:#D2A8FF}"}]}],"toc":{"title":"","searchDepth":2,"depth":2,"links":[{"id":"_1-defining-language-a-nodes","depth":2,"text":"1 - Defining language a nodes"},{"id":"_2-define-processor","depth":2,"text":"2 - Define Processor"},{"id":"_3-define-parser","depth":2,"text":"3 - Define parser"},{"id":"_4-use-the-parse","depth":2,"text":"4 - Use the Parse"}]}},"_type":"markdown","_id":"content:0.core:1.getting-started:simple-usage.md","_source":"content","_file":"0.core/1.getting-started/simple-usage.md","_extension":"md"}